{"OpenedDocuments":"[\"Main.xaml\"]","ProjectBreakpoints":"{\"Value\":{\"Processo/Extract Main Data.xaml\":[{\"ConditionalExpression\":null,\"ActionExpression\":null,\"ExpectedHitCounter\":null,\"ShouldContinueAfterAction\":false,\"IsEnabled\":true,\"ActivityIdRef\":\"TryCatch_16\",\"ActivityId\":\"1.84\",\"ActivityName\":\"Try Execute Transfer\"}],\"Processo/Extract SE16.xaml\":[{\"ConditionalExpression\":null,\"ActionExpression\":null,\"ExpectedHitCounter\":null,\"ShouldContinueAfterAction\":false,\"IsEnabled\":true,\"ActivityIdRef\":\"TryCatch_4\",\"ActivityId\":\"1.80\",\"ActivityName\":\"Try To Execute Transfer\"}]}}","ProjectWatches":"{\"Value\":[]}"}